rsync_time_machine.py
rsync_time_machine-1.4.1.dist-info/licenses/LICENSE
rsync_time_machine-1.4.1.dist-info/METADATA
rsync_time_machine-1.4.1.dist-info/WHEEL
rsync_time_machine-1.4.1.dist-info/entry_points.txt
rsync_time_machine-1.4.1.dist-info/top_level.txt
rsync_time_machine-1.4.1.dist-info/RECORD
