Metadata-Version: 2.4
Name: rsync-time-machine
Version: 1.4.1
Summary: rsync-time-machine.py is a wrapper around rsync to make it easier to create and maintain Time Machine style backups.
Author-email: Bas Nijholt <bas@nijho.lt>
Project-URL: Homepage, https://github.com/basnijholt/rsync-time-machine.py
Requires-Python: >=3.7
License-File: LICENSE
Provides-Extra: test
Requires-Dist: pytest; extra == "test"
Requires-Dist: pre-commit; extra == "test"
Requires-Dist: coverage; extra == "test"
Requires-Dist: pytest-cov; extra == "test"
Provides-Extra: docs
Dynamic: license-file
